aster/__init__.py
aster/__main__.py
aster/errors.py
aster/http.py
aster/wrapper.py
aster.db-0.0.1.dist-info/LICENSE
aster.db-0.0.1.dist-info/METADATA
aster.db-0.0.1.dist-info/WHEEL
aster.db-0.0.1.dist-info/top_level.txt
aster.db-0.0.1.dist-info/RECORD
